arc_memory/__init__.py
arc_memory/__main__.py
arc_memory/config.py
arc_memory/dependencies.py
arc_memory/errors.py
arc_memory/export.py
arc_memory/logging_conf.py
arc_memory/plugins.py
arc_memory/scheduler.py
arc_memory/semantic_search.py
arc_memory/telemetry.py
arc_memory/trace.py
arc_memory/attestation/__init__.py
arc_memory/attestation/write_attest.py
arc_memory/auth/__init__.py
arc_memory/auth/default_credentials.py
arc_memory/auth/github.py
arc_memory/auth/linear.py
arc_memory/auto_refresh/__init__.py
arc_memory/auto_refresh/core.py
arc_memory/auto_refresh/sources/__init__.py
arc_memory/auto_refresh/sources/adr.py
arc_memory/auto_refresh/sources/github.py
arc_memory/auto_refresh/sources/linear.py
arc_memory/cli/__init__.py
arc_memory/cli/auth.py
arc_memory/cli/build.py
arc_memory/cli/doctor.py
arc_memory/cli/export.py
arc_memory/cli/migrate.py
arc_memory/cli/refresh.py
arc_memory/cli/relate.py
arc_memory/cli/repo.py
arc_memory/cli/rl.py
arc_memory/cli/serve.py
arc_memory/cli/trace.py
arc_memory/cli/why.py
arc_memory/db/__init__.py
arc_memory/db/base.py
arc_memory/db/metadata.py
arc_memory/db/neo4j_adapter.py
arc_memory/db/sqlite_adapter.py
arc_memory/ingest/__init__.py
arc_memory/ingest/adr.py
arc_memory/ingest/change_patterns.py
arc_memory/ingest/code_analysis.py
arc_memory/ingest/git.py
arc_memory/ingest/github.py
arc_memory/ingest/github_fetcher.py
arc_memory/ingest/github_graphql.py
arc_memory/ingest/github_rest.py
arc_memory/ingest/linear.py
arc_memory/llm/__init__.py
arc_memory/llm/ollama_client.py
arc_memory/llm/openai_client.py
arc_memory/migrations/__init__.py
arc_memory/migrations/add_architecture_schema.py
arc_memory/migrations/add_enhanced_schema.py
arc_memory/migrations/add_metadata_column.py
arc_memory/migrations/add_repo_id_column.py
arc_memory/migrations/add_timestamp_column.py
arc_memory/process/__init__.py
arc_memory/process/architecture_extraction.py
arc_memory/process/causal_extraction.py
arc_memory/process/kgot.py
arc_memory-0.7.4.data/data/arc_memory-0.7.4.dist-info/licenses/LICENSE
arc_memory-0.7.4.dist-info/METADATA
arc_memory-0.7.4.dist-info/WHEEL
arc_memory-0.7.4.dist-info/entry_points.txt
arc_memory-0.7.4.dist-info/licenses/LICENSE
arc_memory-0.7.4.dist-info/RECORD
