Metadata-Version: 2.4
Name: arc-memory
Version: 0.7.4
Summary: Arc Memory - Local bi-temporal knowledge graph for code repositories
Project-URL: Homepage, https://www.arc.computer
Project-URL: Repository, https://github.com/Arc-Computer/arc-memory
Project-URL: Bug Tracker, https://github.com/Arc-Computer/arc-memory/issues
Author-email: Jarrod Barnes <jbarnes850@gmail.com>
License-Expression: MIT
License-File: LICENSE
Classifier: Development Status :: 4 - Beta
Classifier: Intended Audience :: Developers
Classifier: License :: OSI Approved :: MIT License
Classifier: Programming Language :: Python :: 3
Classifier: Programming Language :: Python :: 3.10
Classifier: Programming Language :: Python :: 3.11
Classifier: Programming Language :: Python :: 3.12
Classifier: Topic :: Software Development :: Libraries :: Python Modules
Classifier: Topic :: Software Development :: Version Control :: Git
Requires-Python: >=3.10
Requires-Dist: aiohttp<4.0.0,>=3.8.0
Requires-Dist: apsw<4.0.0,>=3.40.0
Requires-Dist: cryptography<44.0.0,>=43.0.0
Requires-Dist: gitpython<4.0.0,>=3.1.30
Requires-Dist: gql<4.0.0,>=3.4.0
Requires-Dist: keyring<24.0.0,>=23.13.1
Requires-Dist: markdown-it-py<3.0.0,>=2.2.0
Requires-Dist: matplotlib<4.0.0,>=3.5.0
Requires-Dist: networkx<4.0.0,>=3.0
Requires-Dist: pydantic<3.0.0,>=2.0.0
Requires-Dist: pyjwt<3.0.0,>=2.6.0
Requires-Dist: python-dotenv<2.0.0,>=1.0.0
Requires-Dist: pyyaml<7.0.0,>=6.0
Requires-Dist: requests<3.0.0,>=2.28.0
Requires-Dist: rich<14.0.0,>=13.0.0
Requires-Dist: tqdm<5.0.0,>=4.65.0
Requires-Dist: typer<0.10.0,>=0.9.0
Requires-Dist: zstandard<0.21.0,>=0.20.0
Provides-Extra: cli
Requires-Dist: keyring<24.0.0,>=23.13.1; extra == 'cli'
Requires-Dist: rich<14.0.0,>=13.0.0; extra == 'cli'
Requires-Dist: tqdm<5.0.0,>=4.65.0; extra == 'cli'
Requires-Dist: typer<0.10.0,>=0.9.0; extra == 'cli'
Provides-Extra: dev
Requires-Dist: black<24.0.0,>=23.3.0; extra == 'dev'
Requires-Dist: isort<6.0.0,>=5.12.0; extra == 'dev'
Requires-Dist: mypy<2.0.0,>=1.3.0; extra == 'dev'
Requires-Dist: pre-commit<4.0.0,>=3.3.2; extra == 'dev'
Requires-Dist: pytest-asyncio<0.22.0,>=0.21.0; extra == 'dev'
Requires-Dist: pytest-cov<5.0.0,>=4.1.0; extra == 'dev'
Requires-Dist: pytest<8.0.0,>=7.3.1; extra == 'dev'
Requires-Dist: responses<0.24.0,>=0.23.1; extra == 'dev'
Requires-Dist: ruff<0.1.0,>=0.0.272; extra == 'dev'
Provides-Extra: docs
Requires-Dist: mkdocs-material<10.0.0,>=9.0.0; extra == 'docs'
Requires-Dist: mkdocs<2.0.0,>=1.4.0; extra == 'docs'
Requires-Dist: mkdocstrings<0.21.0,>=0.20.0; extra == 'docs'
Provides-Extra: frameworks
Requires-Dist: langchain-core<0.2.0,>=0.1.0; extra == 'frameworks'
Requires-Dist: langchain-openai<0.1.0,>=0.0.1; extra == 'frameworks'
Requires-Dist: langchain<0.1.0,>=0.0.267; extra == 'frameworks'
Requires-Dist: langgraph<0.1.0,>=0.0.15; extra == 'frameworks'
Requires-Dist: openai<2.0.0,>=1.0.0; extra == 'frameworks'
Provides-Extra: langchain
Requires-Dist: langchain-core<0.2.0,>=0.1.0; extra == 'langchain'
Requires-Dist: langchain-openai<0.1.0,>=0.0.1; extra == 'langchain'
Requires-Dist: langchain<0.1.0,>=0.0.267; extra == 'langchain'
Provides-Extra: langgraph
Requires-Dist: langchain-core<0.2.0,>=0.1.0; extra == 'langgraph'
Requires-Dist: langchain-openai<0.1.0,>=0.0.1; extra == 'langgraph'
Requires-Dist: langgraph<0.1.0,>=0.0.15; extra == 'langgraph'
Provides-Extra: openai
Requires-Dist: openai<2.0.0,>=1.0.0; extra == 'openai'
Provides-Extra: rl
Requires-Dist: matplotlib<4.0.0,>=3.5.0; extra == 'rl'
Requires-Dist: numpy<2.0.0,>=1.23.0; extra == 'rl'
Provides-Extra: telemetry
Requires-Dist: posthog<4.0.0,>=3.0.1; extra == 'telemetry'
Provides-Extra: test
Requires-Dist: pytest-asyncio<0.22.0,>=0.21.0; extra == 'test'
Requires-Dist: pytest-cov<5.0.0,>=4.1.0; extra == 'test'
Requires-Dist: pytest<8.0.0,>=7.3.1; extra == 'test'
Requires-Dist: responses<0.24.0,>=0.23.1; extra == 'test'
